ui_map_parser/__init__.py
ui_map_parser/ui_map_parser.py
ui_map_parser/__pycache__/__init__.cpython-37.pyc
ui_map_parser/__pycache__/ui_map_parser.cpython-37.pyc
ui_map_parser-1.0.0.dist-info/LICENSE
ui_map_parser-1.0.0.dist-info/METADATA
ui_map_parser-1.0.0.dist-info/WHEEL
ui_map_parser-1.0.0.dist-info/top_level.txt
ui_map_parser-1.0.0.dist-info/RECORD
