Metadata-Version: 2.1
Name: ui-map-parser
Version: 1.0.0
Summary: UI map parser.
Home-page: UNKNOWN
Author: Max Biloborodko
Author-email: f1ashhimself@gmail.com
License: UNKNOWN
Platform: UNKNOWN
